{
  "date": "20260501",
  "source_csv": "日报表_广东汕头市雅威机电实业0.12MW#0.257MWh工商储项目_20260502113457.csv",
  "generated_at": "2026-05-10T01:43:49",
  "storage_system": {
    "label": "当前储能系统(250度)",
    "capacity_kwh": 257.0,
    "max_power_kw": 120.0
  },
  "period_order": [
    "峰",
    "平",
    "谷"
  ],
  "period_stats": [
    {
      "period": "峰",
      "photovoltaic_generation_kwh": 579.8789,
      "storage_charge_kwh": 203.275,
      "storage_discharge_kwh": 160.5167,
      "factory_load_kwh": 300.0,
      "charging_pile_load_kwh": 264.7311,
      "grid_purchase_kwh": 36.9555,
      "grid_sale_kwh": 82.6838,
      "factory_savings_revenue": 206.5471,
      "photovoltaic_to_load_kwh": 312.3922,
      "photovoltaic_to_factory_kwh": 210.7691,
      "photovoltaic_to_storage_kwh": 184.8028,
      "photovoltaic_to_grid_kwh": 82.6838,
      "grid_to_load_kwh": 18.4833,
      "grid_to_storage_kwh": 18.4722
    },
    {
      "period": "平",
      "photovoltaic_generation_kwh": 407.1062,
      "storage_charge_kwh": 28.7167,
      "storage_discharge_kwh": 314.7417,
      "factory_load_kwh": 150.0,
      "charging_pile_load_kwh": 1194.9209,
      "grid_purchase_kwh": 659.025,
      "grid_sale_kwh": 9.8167,
      "factory_savings_revenue": 74.3842,
      "photovoltaic_to_load_kwh": 373.5395,
      "photovoltaic_to_factory_kwh": 126.5535,
      "photovoltaic_to_storage_kwh": 23.75,
      "photovoltaic_to_grid_kwh": 9.8167,
      "grid_to_load_kwh": 654.0583,
      "grid_to_storage_kwh": 4.9667
    },
    {
      "period": "谷",
      "photovoltaic_generation_kwh": 47.147,
      "storage_charge_kwh": 269.725,
      "storage_discharge_kwh": 0.0,
      "factory_load_kwh": 50.0,
      "charging_pile_load_kwh": 1198.7303,
      "grid_purchase_kwh": 1471.3083,
      "grid_sale_kwh": 0.0,
      "factory_savings_revenue": 7.3289,
      "photovoltaic_to_load_kwh": 47.147,
      "photovoltaic_to_factory_kwh": 30.465,
      "photovoltaic_to_storage_kwh": 0.0,
      "photovoltaic_to_grid_kwh": 0.0,
      "grid_to_load_kwh": 1201.5833,
      "grid_to_storage_kwh": 269.725
    }
  ],
  "hourly_stats": [
    {
      "hour": "00:00",
      "period": "谷",
      "photovoltaic_generation_kwh": 0.0655,
      "storage_charge_kwh": 44.9167,
      "storage_discharge_kwh": 0.0,
      "factory_load_kwh": 0.0,
      "charging_pile_load_kwh": 375.2572,
      "grid_purchase_kwh": 420.1083,
      "grid_sale_kwh": 0.0,
      "factory_savings_revenue": 0.0,
      "photovoltaic_to_load_kwh": 0.0655,
      "photovoltaic_to_factory_kwh": 0.0,
      "photovoltaic_to_storage_kwh": 0.0,
      "photovoltaic_to_grid_kwh": 0.0,
      "grid_to_load_kwh": 375.1917,
      "grid_to_storage_kwh": 44.9167
    },
    {
      "hour": "01:00",
      "period": "谷",
      "photovoltaic_generation_kwh": 0.2085,
      "storage_charge_kwh": 44.9667,
      "storage_discharge_kwh": 0.0,
      "factory_load_kwh": 0.0,
      "charging_pile_load_kwh": 197.7252,
      "grid_purchase_kwh": 242.4833,
      "grid_sale_kwh": 0.0,
      "factory_savings_revenue": 0.0,
      "photovoltaic_to_load_kwh": 0.2085,
      "photovoltaic_to_factory_kwh": 0.0,
      "photovoltaic_to_storage_kwh": 0.0,
      "photovoltaic_to_grid_kwh": 0.0,
      "grid_to_load_kwh": 197.5167,
      "grid_to_storage_kwh": 44.9667
    },
    {
      "hour": "02:00",
      "period": "谷",
      "photovoltaic_generation_kwh": 0.3515,
      "storage_charge_kwh": 44.9667,
      "storage_discharge_kwh": 0.0,
      "factory_load_kwh": 0.0,
      "charging_pile_load_kwh": 76.9848,
      "grid_purchase_kwh": 121.6,
      "grid_sale_kwh": 0.0,
      "factory_savings_revenue": 0.0,
      "photovoltaic_to_load_kwh": 0.3515,
      "photovoltaic_to_factory_kwh": 0.0,
      "photovoltaic_to_storage_kwh": 0.0,
      "photovoltaic_to_grid_kwh": 0.0,
      "grid_to_load_kwh": 76.6333,
      "grid_to_storage_kwh": 44.9667
    },
    {
      "hour": "03:00",
      "period": "谷",
      "photovoltaic_generation_kwh": 0.4945,
      "storage_charge_kwh": 44.95,
      "storage_discharge_kwh": 0.0,
      "factory_load_kwh": 0.0,
      "charging_pile_load_kwh": 139.4862,
      "grid_purchase_kwh": 183.9417,
      "grid_sale_kwh": 0.0,
      "factory_savings_revenue": 0.0,
      "photovoltaic_to_load_kwh": 0.4945,
      "photovoltaic_to_factory_kwh": 0.0,
      "photovoltaic_to_storage_kwh": 0.0,
      "photovoltaic_to_grid_kwh": 0.0,
      "grid_to_load_kwh": 138.9917,
      "grid_to_storage_kwh": 44.95
    },
    {
      "hour": "04:00",
      "period": "谷",
      "photovoltaic_generation_kwh": 0.6375,
      "storage_charge_kwh": 44.975,
      "storage_discharge_kwh": 0.0,
      "factory_load_kwh": 0.0,
      "charging_pile_load_kwh": 40.9042,
      "grid_purchase_kwh": 85.2417,
      "grid_sale_kwh": 0.0,
      "factory_savings_revenue": 0.0,
      "photovoltaic_to_load_kwh": 0.6375,
      "photovoltaic_to_factory_kwh": 0.0,
      "photovoltaic_to_storage_kwh": 0.0,
      "photovoltaic_to_grid_kwh": 0.0,
      "grid_to_load_kwh": 40.2667,
      "grid_to_storage_kwh": 44.975
    },
    {
      "hour": "05:00",
      "period": "谷",
      "photovoltaic_generation_kwh": 0.934,
      "storage_charge_kwh": 44.95,
      "storage_discharge_kwh": 0.0,
      "factory_load_kwh": 0.0,
      "charging_pile_load_kwh": 8.0673,
      "grid_purchase_kwh": 52.0833,
      "grid_sale_kwh": 0.0,
      "factory_savings_revenue": 0.0,
      "photovoltaic_to_load_kwh": 0.934,
      "photovoltaic_to_factory_kwh": 0.0,
      "photovoltaic_to_storage_kwh": 0.0,
      "photovoltaic_to_grid_kwh": 0.0,
      "grid_to_load_kwh": 7.1333,
      "grid_to_storage_kwh": 44.95
    },
    {
      "hour": "06:00",
      "period": "谷",
      "photovoltaic_generation_kwh": 13.9905,
      "storage_charge_kwh": 0.0,
      "storage_discharge_kwh": 0.0,
      "factory_load_kwh": 0.0,
      "charging_pile_load_kwh": 118.3155,
      "grid_purchase_kwh": 104.325,
      "grid_sale_kwh": 0.0,
      "factory_savings_revenue": 0.0,
      "photovoltaic_to_load_kwh": 13.9905,
      "photovoltaic_to_factory_kwh": 0.0,
      "photovoltaic_to_storage_kwh": 0.0,
      "photovoltaic_to_grid_kwh": 0.0,
      "grid_to_load_kwh": 104.325,
      "grid_to_storage_kwh": 0.0
    },
    {
      "hour": "07:00",
      "period": "谷",
      "photovoltaic_generation_kwh": 30.465,
      "storage_charge_kwh": 0.0,
      "storage_discharge_kwh": 0.0,
      "factory_load_kwh": 50.0,
      "charging_pile_load_kwh": 241.99,
      "grid_purchase_kwh": 261.525,
      "grid_sale_kwh": 0.0,
      "factory_savings_revenue": 7.3289,
      "photovoltaic_to_load_kwh": 30.465,
      "photovoltaic_to_factory_kwh": 30.465,
      "photovoltaic_to_storage_kwh": 0.0,
      "photovoltaic_to_grid_kwh": 0.0,
      "grid_to_load_kwh": 261.525,
      "grid_to_storage_kwh": 0.0
    },
    {
      "hour": "08:00",
      "period": "平",
      "photovoltaic_generation_kwh": 33.1475,
      "storage_charge_kwh": 0.0,
      "storage_discharge_kwh": 103.2,
      "factory_load_kwh": 50.0,
      "charging_pile_load_kwh": 180.5349,
      "grid_purchase_kwh": 93.7917,
      "grid_sale_kwh": 0.0,
      "factory_savings_revenue": 19.4831,
      "photovoltaic_to_load_kwh": 33.1475,
      "photovoltaic_to_factory_kwh": 33.1475,
      "photovoltaic_to_storage_kwh": 0.0,
      "photovoltaic_to_grid_kwh": 0.0,
      "grid_to_load_kwh": 93.7917,
      "grid_to_storage_kwh": 0.0
    },
    {
      "hour": "09:00",
      "period": "平",
      "photovoltaic_generation_kwh": 51.7897,
      "storage_charge_kwh": 4.8583,
      "storage_discharge_kwh": 4.5833,
      "factory_load_kwh": 50.0,
      "charging_pile_load_kwh": 9.6587,
      "grid_purchase_kwh": 5.9583,
      "grid_sale_kwh": 0.0,
      "factory_savings_revenue": 25.5127,
      "photovoltaic_to_load_kwh": 48.9563,
      "photovoltaic_to_factory_kwh": 43.406,
      "photovoltaic_to_storage_kwh": 2.8333,
      "photovoltaic_to_grid_kwh": 0.0,
      "grid_to_load_kwh": 3.9333,
      "grid_to_storage_kwh": 2.025
    },
    {
      "hour": "10:00",
      "period": "峰",
      "photovoltaic_generation_kwh": 121.1314,
      "storage_charge_kwh": 45.8,
      "storage_discharge_kwh": 1.775,
      "factory_load_kwh": 50.0,
      "charging_pile_load_kwh": 37.1612,
      "grid_purchase_kwh": 7.6167,
      "grid_sale_kwh": 0.0,
      "factory_savings_revenue": 46.6091,
      "photovoltaic_to_load_kwh": 81.2647,
      "photovoltaic_to_factory_kwh": 47.5618,
      "photovoltaic_to_storage_kwh": 39.8667,
      "photovoltaic_to_grid_kwh": 0.0,
      "grid_to_load_kwh": 1.6833,
      "grid_to_storage_kwh": 5.9333
    },
    {
      "hour": "11:00",
      "period": "峰",
      "photovoltaic_generation_kwh": 230.229,
      "storage_charge_kwh": 61.5833,
      "storage_discharge_kwh": 0.0,
      "factory_load_kwh": 50.0,
      "charging_pile_load_kwh": 44.9848,
      "grid_purchase_kwh": 1.975,
      "grid_sale_kwh": 79.8126,
      "factory_savings_revenue": 44.9054,
      "photovoltaic_to_load_kwh": 90.8081,
      "photovoltaic_to_factory_kwh": 45.8232,
      "photovoltaic_to_storage_kwh": 59.6083,
      "photovoltaic_to_grid_kwh": 79.8126,
      "grid_to_load_kwh": 0.0,
      "grid_to_storage_kwh": 1.975
    },
    {
      "hour": "12:00",
      "period": "平",
      "photovoltaic_generation_kwh": 147.2052,
      "storage_charge_kwh": 0.0,
      "storage_discharge_kwh": 97.6667,
      "factory_load_kwh": 0.0,
      "charging_pile_load_kwh": 332.4052,
      "grid_purchase_kwh": 94.4583,
      "grid_sale_kwh": 6.925,
      "factory_savings_revenue": 0.0,
      "photovoltaic_to_load_kwh": 140.2802,
      "photovoltaic_to_factory_kwh": 0.0,
      "photovoltaic_to_storage_kwh": 0.0,
      "photovoltaic_to_grid_kwh": 6.925,
      "grid_to_load_kwh": 94.4583,
      "grid_to_storage_kwh": 0.0
    },
    {
      "hour": "13:00",
      "period": "平",
      "photovoltaic_generation_kwh": 170.6037,
      "storage_charge_kwh": 23.0,
      "storage_discharge_kwh": 62.3167,
      "factory_load_kwh": 50.0,
      "charging_pile_load_kwh": 182.7203,
      "grid_purchase_kwh": 25.6917,
      "grid_sale_kwh": 2.8917,
      "factory_savings_revenue": 29.3884,
      "photovoltaic_to_load_kwh": 146.7953,
      "photovoltaic_to_factory_kwh": 50.0,
      "photovoltaic_to_storage_kwh": 20.9167,
      "photovoltaic_to_grid_kwh": 2.8917,
      "grid_to_load_kwh": 23.6083,
      "grid_to_storage_kwh": 2.0833
    },
    {
      "hour": "14:00",
      "period": "峰",
      "photovoltaic_generation_kwh": 56.1129,
      "storage_charge_kwh": 38.2167,
      "storage_discharge_kwh": 1.7833,
      "factory_load_kwh": 50.0,
      "charging_pile_load_kwh": 6.8905,
      "grid_purchase_kwh": 2.1888,
      "grid_sale_kwh": 2.8713,
      "factory_savings_revenue": 11.8397,
      "photovoltaic_to_load_kwh": 16.6388,
      "photovoltaic_to_factory_kwh": 12.0817,
      "photovoltaic_to_storage_kwh": 36.6028,
      "photovoltaic_to_grid_kwh": 2.8713,
      "grid_to_load_kwh": 0.575,
      "grid_to_storage_kwh": 1.6138
    },
    {
      "hour": "15:00",
      "period": "峰",
      "photovoltaic_generation_kwh": 73.0954,
      "storage_charge_kwh": 34.9667,
      "storage_discharge_kwh": 18.5917,
      "factory_load_kwh": 50.0,
      "charging_pile_load_kwh": 24.9038,
      "grid_purchase_kwh": 6.075,
      "grid_sale_kwh": 0.0,
      "factory_savings_revenue": 35.2576,
      "photovoltaic_to_load_kwh": 41.6204,
      "photovoltaic_to_factory_kwh": 35.9783,
      "photovoltaic_to_storage_kwh": 31.475,
      "photovoltaic_to_grid_kwh": 0.0,
      "grid_to_load_kwh": 2.5833,
      "grid_to_storage_kwh": 3.4917
    },
    {
      "hour": "16:00",
      "period": "峰",
      "photovoltaic_generation_kwh": 46.5112,
      "storage_charge_kwh": 13.975,
      "storage_discharge_kwh": 11.2417,
      "factory_load_kwh": 50.0,
      "charging_pile_load_kwh": 6.5775,
      "grid_purchase_kwh": 5.7417,
      "grid_sale_kwh": 0.0,
      "factory_savings_revenue": 34.1874,
      "photovoltaic_to_load_kwh": 34.8862,
      "photovoltaic_to_factory_kwh": 34.8862,
      "photovoltaic_to_storage_kwh": 11.625,
      "photovoltaic_to_grid_kwh": 0.0,
      "grid_to_load_kwh": 3.3917,
      "grid_to_storage_kwh": 2.35
    },
    {
      "hour": "17:00",
      "period": "峰",
      "photovoltaic_generation_kwh": 46.0398,
      "storage_charge_kwh": 8.7333,
      "storage_discharge_kwh": 37.025,
      "factory_load_kwh": 50.0,
      "charging_pile_load_kwh": 41.1874,
      "grid_purchase_kwh": 7.1917,
      "grid_sale_kwh": 0.0,
      "factory_savings_revenue": 33.748,
      "photovoltaic_to_load_kwh": 40.4148,
      "photovoltaic_to_factory_kwh": 34.4378,
      "photovoltaic_to_storage_kwh": 5.625,
      "photovoltaic_to_grid_kwh": 0.0,
      "grid_to_load_kwh": 4.0833,
      "grid_to_storage_kwh": 3.1083
    },
    {
      "hour": "18:00",
      "period": "峰",
      "photovoltaic_generation_kwh": 6.7592,
      "storage_charge_kwh": 0.0,
      "storage_discharge_kwh": 90.1,
      "factory_load_kwh": 0.0,
      "charging_pile_load_kwh": 103.0258,
      "grid_purchase_kwh": 6.1667,
      "grid_sale_kwh": 0.0,
      "factory_savings_revenue": 0.0,
      "photovoltaic_to_load_kwh": 6.7592,
      "photovoltaic_to_factory_kwh": 0.0,
      "photovoltaic_to_storage_kwh": 0.0,
      "photovoltaic_to_grid_kwh": 0.0,
      "grid_to_load_kwh": 6.1667,
      "grid_to_storage_kwh": 0.0
    },
    {
      "hour": "19:00",
      "period": "平",
      "photovoltaic_generation_kwh": 1.197,
      "storage_charge_kwh": 0.0,
      "storage_discharge_kwh": 46.975,
      "factory_load_kwh": 0.0,
      "charging_pile_load_kwh": 195.2387,
      "grid_purchase_kwh": 147.0667,
      "grid_sale_kwh": 0.0,
      "factory_savings_revenue": 0.0,
      "photovoltaic_to_load_kwh": 1.197,
      "photovoltaic_to_factory_kwh": 0.0,
      "photovoltaic_to_storage_kwh": 0.0,
      "photovoltaic_to_grid_kwh": 0.0,
      "grid_to_load_kwh": 147.0667,
      "grid_to_storage_kwh": 0.0
    },
    {
      "hour": "20:00",
      "period": "平",
      "photovoltaic_generation_kwh": 1.197,
      "storage_charge_kwh": 0.175,
      "storage_discharge_kwh": 0.0,
      "factory_load_kwh": 0.0,
      "charging_pile_load_kwh": 97.1553,
      "grid_purchase_kwh": 96.1333,
      "grid_sale_kwh": 0.0,
      "factory_savings_revenue": 0.0,
      "photovoltaic_to_load_kwh": 1.197,
      "photovoltaic_to_factory_kwh": 0.0,
      "photovoltaic_to_storage_kwh": 0.0,
      "photovoltaic_to_grid_kwh": 0.0,
      "grid_to_load_kwh": 95.9583,
      "grid_to_storage_kwh": 0.175
    },
    {
      "hour": "21:00",
      "period": "平",
      "photovoltaic_generation_kwh": 1.197,
      "storage_charge_kwh": 0.0167,
      "storage_discharge_kwh": 0.0,
      "factory_load_kwh": 0.0,
      "charging_pile_load_kwh": 61.647,
      "grid_purchase_kwh": 60.4667,
      "grid_sale_kwh": 0.0,
      "factory_savings_revenue": 0.0,
      "photovoltaic_to_load_kwh": 1.197,
      "photovoltaic_to_factory_kwh": 0.0,
      "photovoltaic_to_storage_kwh": 0.0,
      "photovoltaic_to_grid_kwh": 0.0,
      "grid_to_load_kwh": 60.45,
      "grid_to_storage_kwh": 0.0167
    },
    {
      "hour": "22:00",
      "period": "平",
      "photovoltaic_generation_kwh": 0.5692,
      "storage_charge_kwh": 0.1167,
      "storage_discharge_kwh": 0.0,
      "factory_load_kwh": 0.0,
      "charging_pile_load_kwh": 20.8525,
      "grid_purchase_kwh": 20.4,
      "grid_sale_kwh": 0.0,
      "factory_savings_revenue": 0.0,
      "photovoltaic_to_load_kwh": 0.5692,
      "photovoltaic_to_factory_kwh": 0.0,
      "photovoltaic_to_storage_kwh": 0.0,
      "photovoltaic_to_grid_kwh": 0.0,
      "grid_to_load_kwh": 20.2833,
      "grid_to_storage_kwh": 0.1167
    },
    {
      "hour": "23:00",
      "period": "平",
      "photovoltaic_generation_kwh": 0.2,
      "storage_charge_kwh": 0.55,
      "storage_discharge_kwh": 0.0,
      "factory_load_kwh": 0.0,
      "charging_pile_load_kwh": 114.7083,
      "grid_purchase_kwh": 115.0583,
      "grid_sale_kwh": 0.0,
      "factory_savings_revenue": 0.0,
      "photovoltaic_to_load_kwh": 0.2,
      "photovoltaic_to_factory_kwh": 0.0,
      "photovoltaic_to_storage_kwh": 0.0,
      "photovoltaic_to_grid_kwh": 0.0,
      "grid_to_load_kwh": 114.5083,
      "grid_to_storage_kwh": 0.55
    }
  ],
  "scenarios": {
    "A": {
      "scenario_name": "A",
      "pv_feed_in_price": 0.1,
      "daily_revenue": {
        "total_revenue": 1147.9932,
        "cash_revenue": 859.7329,
        "without_storage_total_revenue": 912.4606,
        "photovoltaic_sale_revenue": {
          "total": 9.25,
          "from_storage": 0.0
        },
        "factory_savings_revenue": {
          "total": 311.597,
          "from_photovoltaic": 288.2602,
          "from_storage": 23.3367
        },
        "charging_pile_revenue": {
          "total": 1628.0032,
          "from_photovoltaic": 257.494,
          "from_grid": 1034.6484,
          "from_storage": 335.8608,
          "service_fee": 377.8608
        },
        "grid_purchase_cost": 777.5203,
        "storage_contribution": {
          "total": 235.5325,
          "charging_pile_revenue": 335.8608,
          "factory_savings_revenue": 23.3367
        },
        "net_revenue_breakdown": {
          "allocation_method": "strict_accounting",
          "pie_chart_ready": true,
          "items": {
            "photovoltaic_sale": {
              "amount": 9.25,
              "share_of_total_revenue": 0.0081
            },
            "factory_savings": {
              "amount": 288.2602,
              "share_of_total_revenue": 0.2511
            },
            "charging_pile": {
              "amount": 850.483,
              "share_of_total_revenue": 0.7408
            }
          },
          "sum_of_items": 1147.9932
        }
      },
      "revenue_components": {
        "photovoltaic": {
          "actual_total": 555.0043,
          "to_grid": 9.25,
          "to_charging_pile": 257.494,
          "to_factory_savings": 288.2602
        },
        "grid": {
          "purchase_cost": 777.5203,
          "to_factory_cost": 9.2004,
          "to_storage_cost": 85.9088,
          "to_charging_pile_revenue": 1034.6484
        },
        "storage": {
          "extra_profit": 235.5325,
          "to_factory_savings": 23.3367,
          "to_charging_pile_revenue": 335.8608
        }
      }
    },
    "B": {
      "scenario_name": "B",
      "pv_feed_in_price": 0.2,
      "daily_revenue": {
        "total_revenue": 1157.2432,
        "cash_revenue": 868.983,
        "without_storage_total_revenue": 942.566,
        "photovoltaic_sale_revenue": {
          "total": 18.5001,
          "from_storage": 0.0
        },
        "factory_savings_revenue": {
          "total": 311.597,
          "from_photovoltaic": 288.2602,
          "from_storage": 23.3367
        },
        "charging_pile_revenue": {
          "total": 1628.0032,
          "from_photovoltaic": 257.494,
          "from_grid": 1034.6484,
          "from_storage": 335.8608,
          "service_fee": 377.8608
        },
        "grid_purchase_cost": 777.5203,
        "storage_contribution": {
          "total": 214.6773,
          "charging_pile_revenue": 335.8608,
          "factory_savings_revenue": 23.3367
        },
        "net_revenue_breakdown": {
          "allocation_method": "strict_accounting",
          "pie_chart_ready": true,
          "items": {
            "photovoltaic_sale": {
              "amount": 18.5001,
              "share_of_total_revenue": 0.016
            },
            "factory_savings": {
              "amount": 288.2602,
              "share_of_total_revenue": 0.2491
            },
            "charging_pile": {
              "amount": 850.4829,
              "share_of_total_revenue": 0.7349
            }
          },
          "sum_of_items": 1157.2432
        }
      },
      "revenue_components": {
        "photovoltaic": {
          "actual_total": 564.2544,
          "to_grid": 18.5001,
          "to_charging_pile": 257.494,
          "to_factory_savings": 288.2602
        },
        "grid": {
          "purchase_cost": 777.5203,
          "to_factory_cost": 9.2004,
          "to_storage_cost": 85.9088,
          "to_charging_pile_revenue": 1034.6484
        },
        "storage": {
          "extra_profit": 214.6773,
          "to_factory_savings": 23.3367,
          "to_charging_pile_revenue": 335.8608
        }
      }
    },
    "C": {
      "scenario_name": "C",
      "pv_feed_in_price": 0.35,
      "daily_revenue": {
        "total_revenue": 1171.1183,
        "cash_revenue": 882.8581,
        "without_storage_total_revenue": 987.724,
        "photovoltaic_sale_revenue": {
          "total": 32.3752,
          "from_storage": 0.0
        },
        "factory_savings_revenue": {
          "total": 311.597,
          "from_photovoltaic": 288.2602,
          "from_storage": 23.3367
        },
        "charging_pile_revenue": {
          "total": 1628.0032,
          "from_photovoltaic": 257.494,
          "from_grid": 1034.6484,
          "from_storage": 335.8608,
          "service_fee": 377.8608
        },
        "grid_purchase_cost": 777.5203,
        "storage_contribution": {
          "total": 183.3943,
          "charging_pile_revenue": 335.8608,
          "factory_savings_revenue": 23.3367
        },
        "net_revenue_breakdown": {
          "allocation_method": "strict_accounting",
          "pie_chart_ready": true,
          "items": {
            "photovoltaic_sale": {
              "amount": 32.3752,
              "share_of_total_revenue": 0.0276
            },
            "factory_savings": {
              "amount": 288.2602,
              "share_of_total_revenue": 0.2461
            },
            "charging_pile": {
              "amount": 850.4829,
              "share_of_total_revenue": 0.7262
            }
          },
          "sum_of_items": 1171.1183
        }
      },
      "revenue_components": {
        "photovoltaic": {
          "actual_total": 578.1294,
          "to_grid": 32.3752,
          "to_charging_pile": 257.494,
          "to_factory_savings": 288.2602
        },
        "grid": {
          "purchase_cost": 777.5203,
          "to_factory_cost": 9.2004,
          "to_storage_cost": 85.9088,
          "to_charging_pile_revenue": 1034.6484
        },
        "storage": {
          "extra_profit": 183.3943,
          "to_factory_savings": 23.3367,
          "to_charging_pile_revenue": 335.8608
        }
      }
    }
  }
}